pymultigit/__init__.py
pymultigit/configs.py
pymultigit/core.py
pymultigit/main.py
pymultigit/static.py
pymultigit/utils/__init__.py
pymultigit/utils/subprocess.py
pymultigit-0.0.95.dist-info/METADATA
pymultigit-0.0.95.dist-info/WHEEL
pymultigit-0.0.95.dist-info/entry_points.txt
pymultigit-0.0.95.dist-info/licenses/LICENSE
pymultigit-0.0.95.dist-info/RECORD
