Metadata-Version: 2.4
Name: pymultigit
Version: 0.0.95
Summary: Pymultigit helps you deal with multiple git repositories
Project-URL: Homepage, https://github.com/veltzer/pymultigit
Project-URL: Bug Tracker, https://github.com/veltzer/pymultigit/issues
Project-URL: Documentation, https://veltzer.github.io/pymultigit
Project-URL: Download, https://pypi.org/project/pymultigit/
Project-URL: Repository, https://github.com/veltzer/pymultigit
Author-email: Mark Veltzer <mark.veltzer@gmail.com>
Maintainer-email: Mark Veltzer <mark.veltzer@gmail.com>
License-Expression: MIT
License-File: LICENSE
Keywords: git,multiple,python,repositories
Classifier: Development Status :: 4 - Beta
Classifier: Environment :: Console
Classifier: License :: OSI Approved :: MIT License
Classifier: Operating System :: OS Independent
Classifier: Programming Language :: Python
Classifier: Programming Language :: Python :: 3
Classifier: Programming Language :: Python :: 3 :: Only
Classifier: Programming Language :: Python :: 3.12
Classifier: Topic :: Utilities
Requires-Python: >=3.12
Requires-Dist: gitpython
Requires-Dist: pyfakeuse
Requires-Dist: pylogconf
Requires-Dist: pytconf
Requires-Dist: venv-run
